wakepsXonbt/__init__.py
wakepsXonbt/wakepsXonbt.py
pywakepsXonbt-0.1.2.dist-info/LICENSE
pywakepsXonbt-0.1.2.dist-info/METADATA
pywakepsXonbt-0.1.2.dist-info/WHEEL
pywakepsXonbt-0.1.2.dist-info/top_level.txt
pywakepsXonbt-0.1.2.dist-info/RECORD
