Metadata-Version: 2.1
Name: pywakepsXonbt
Version: 0.1.2
Summary: A Python library to wakeup PlayStation (ps3, ps4, ps5) on BlueTooth
Home-page: https://github.com/FreeTHX/pywakepsXonbt
Author: FreeTHX
Author-email: freethx.dev@gmail.com
License: Apache License 2.0
Keywords: wake playstation (ps3,ps4,ps5) on bt home assistant
Classifier: Development Status :: 3 - Alpha
Classifier: Intended Audience :: Developers
Classifier: Topic :: Home Automation
Classifier: Topic :: Software Development :: Libraries :: Python Modules
Classifier: License :: OSI Approved :: Apache Software License
Classifier: Programming Language :: Python :: 3
Classifier: Programming Language :: Python :: 3.4
Classifier: Programming Language :: Python :: 3.5
Classifier: Programming Language :: Python :: 3.6
Classifier: Programming Language :: Python :: 3.7
Classifier: Programming Language :: Python :: 3.8
Classifier: Programming Language :: Python :: 3.9
Classifier: Programming Language :: Python :: 3.10
Classifier: Programming Language :: Python :: 3.11
License-File: LICENSE
Requires-Dist: pyusb
